hk80/__init__.py
hk80/coordinates.py
hk80/hk80.py
hk80-1.0.1.dist-info/LICENSE
hk80-1.0.1.dist-info/METADATA
hk80-1.0.1.dist-info/WHEEL
hk80-1.0.1.dist-info/top_level.txt
hk80-1.0.1.dist-info/RECORD
