Metadata-Version: 2.1
Name: hk80
Version: 1.0.1
Summary: Hong Kong 1980 Grid coordinates conversion library in Python
Home-page: https://github.com/MacroYau/PyHK80
Author: Macro Yau
Author-email: macroyau.development@gmail.com
License: MIT
Platform: UNKNOWN
Classifier: Programming Language :: Python
Classifier: License :: OSI Approved :: MIT License
Classifier: Operating System :: OS Independent
Requires-Dist: pyproj (==2.1.3)
